mesm/__init__.py
mesm/secret_manager.py
mesm-0.1.0.dist-info/METADATA
mesm-0.1.0.dist-info/WHEEL
mesm-0.1.0.dist-info/RECORD
