Metadata-Version: 2.3
Name: mesm
Version: 0.1.0
Summary: library for secure, scalable, and efficient access to Google Cloud Secret Manager across multiple environments.
License: MIT
Author: Mohammad Khodaparastan
Author-email: mohammad@khodaparastan.com
Requires-Python: >=3.13,<4
Classifier: License :: OSI Approved :: MIT License
Classifier: Programming Language :: Python :: 3
Classifier: Programming Language :: Python :: 3.13
Requires-Dist: cachetools (>=2.0.0,<6.0)
Requires-Dist: prometheus-client (>=0.22.1,<0.23.0)
Requires-Dist: pydantic (>=2.11.5,<3.0.0)
Requires-Dist: pydantic-settings (>=2.9.1,<3.0.0)
Requires-Dist: pyyaml (>=6.0.2,<7.0.0)
Requires-Dist: structlog (>=25.4.0,<26.0.0)
Requires-Dist: tenacity (>=9.1.2,<10.0.0)
